sunscreen_fhe-0.1.2.dist-info/METADATA
sunscreen_fhe-0.1.2.dist-info/WHEEL
sunscreen_fhe-0.1.2.dist-info/licenses/LICENSE
sunscreen_fhe/__init__.py
sunscreen_fhe/_native.pyd
sunscreen_fhe/_native.pyi
sunscreen_fhe/builder.py
sunscreen_fhe/outputs.py
sunscreen_fhe/parameters.py
sunscreen_fhe/py.typed
sunscreen_fhe/validation.py
sunscreen_fhe-0.1.2.dist-info/RECORD
