Metadata-Version: 2.4
Name: sunscreen-fhe
Version: 0.1.2
Classifier: Programming Language :: Python :: 3
Classifier: Programming Language :: Python :: 3.10
Classifier: Programming Language :: Python :: 3.11
Classifier: Programming Language :: Python :: 3.12
Classifier: Programming Language :: Python :: 3.13
Classifier: Programming Language :: Python :: 3.14
Classifier: Programming Language :: Python :: Implementation :: CPython
Classifier: Programming Language :: Rust
Classifier: License :: OSI Approved :: MIT License
Classifier: Operating System :: MacOS
Classifier: Operating System :: POSIX :: Linux
Classifier: Operating System :: Microsoft :: Windows
Classifier: Topic :: Security :: Cryptography
License-File: LICENSE
Summary: Python client for FHE program runner
Keywords: fhe,homomorphic-encryption,cryptography,parasol,tfhe,privacy
Author-email: Sunscreen <hello@sunscreen.tech>
License-Expression: MIT
Requires-Python: >=3.10
Project-URL: Bug Tracker, https://github.com/Sunscreen-tech/spf-runner/issues
